<?xml version="1.0" encoding="UTF-8"?>
<root><element><id><![CDATA[1]]></id><name><![CDATA[Hotel NH Eurobuilding]]></name><url><![CDATA[http://www.nh-hoteles.es/nh/es/hoteles/espana/madrid/nh-eurobuilding.html]]></url><email><![CDATA[nheurobuilding@nh-hotels.com ]]></email><phone><![CDATA[913537300]]></phone><address><![CDATA[Calle Padre Damián, 23
28036 Madrid]]></address><gps_coords><![CDATA[40.45824,-3.685814]]></gps_coords><locations><element><id><![CDATA[5]]></id><name><![CDATA[Salón Madrid]]></name><gps_coords><![CDATA[]]></gps_coords></element><element><id><![CDATA[6]]></id><name><![CDATA[Sala Bruselas]]></name><gps_coords><![CDATA[]]></gps_coords></element><element><id><![CDATA[8]]></id><name><![CDATA[Sala Londres]]></name><gps_coords><![CDATA[]]></gps_coords></element><element><id><![CDATA[9]]></id><name><![CDATA[Sala París]]></name><gps_coords><![CDATA[]]></gps_coords></element><element><id><![CDATA[10]]></id><name><![CDATA[Sala Viena]]></name><gps_coords><![CDATA[]]></gps_coords></element><element><id><![CDATA[11]]></id><name><![CDATA[Sala Roma I]]></name><gps_coords><![CDATA[]]></gps_coords></element><element><id><![CDATA[12]]></id><name><![CDATA[Sala Roma II]]></name><gps_coords><![CDATA[]]></gps_coords></element><element><id><![CDATA[14]]></id><name><![CDATA[Hotel NH Eurobuilding]]></name><gps_coords><![CDATA[]]></gps_coords></element><element><id><![CDATA[16]]></id><name><![CDATA[Sala Berlín]]></name><gps_coords><![CDATA[]]></gps_coords></element><element><id><![CDATA[17]]></id><name><![CDATA[Hall Plaza Mayor]]></name><gps_coords><![CDATA[]]></gps_coords></element><element><id><![CDATA[19]]></id><name><![CDATA[Sala Magerit]]></name><gps_coords><![CDATA[]]></gps_coords></element></locations></element><element><id><![CDATA[2]]></id><name><![CDATA[
Real Academia de Ciencias Exactas Fisicas y Naturales]]></name><url><![CDATA[http://www.rac.es/1/1_1.php]]></url><email><![CDATA[secretaria@rac.es]]></email><phone><![CDATA[917014230 ]]></phone><address><![CDATA[Calle Valverde, 22]]></address><gps_coords><![CDATA[40.42195,-3.701714]]></gps_coords><locations><element><id><![CDATA[13]]></id><name><![CDATA[Real Academia de Ciencias]]></name><gps_coords><![CDATA[]]></gps_coords></element></locations></element><element><id><![CDATA[3]]></id><name><![CDATA[Hotel Meliá Princesa]]></name><url><![CDATA[http://es.melia.com/hoteles/espana/madrid/melia-madrid-princesa/index.html]]></url><email><![CDATA[melia.madrid.princesa@melia.com]]></email><phone><![CDATA[915418200]]></phone><address><![CDATA[Calle de la Princesa, 27
28008 Madrid]]></address><gps_coords><![CDATA[40.427441,-3.713963]]></gps_coords><locations><element><id><![CDATA[15]]></id><name><![CDATA[Hotel Melia Princesa]]></name><gps_coords><![CDATA[]]></gps_coords></element></locations></element><element><id><![CDATA[4]]></id><name><![CDATA[Restaurante Samarkanda Puerta de Atocha]]></name><url><![CDATA[http://www.restaurantesamarkanda.com/]]></url><email><![CDATA[]]></email><phone><![CDATA[915309746]]></phone><address><![CDATA[Jardín Botánico Estación Puerta de Atocha, Gta. Carlos V, 5, 28012 Madrid]]></address><gps_coords><![CDATA[40.406446,-3.690687]]></gps_coords><locations><element><id><![CDATA[18]]></id><name><![CDATA[Restaurante Samarkanda (Estación Puerta de Atocha)]]></name><gps_coords><![CDATA[]]></gps_coords></element></locations></element></root>